LICENSE
MANIFEST.in
README
README.md
requirements.txt
setup.cfg
setup.py
staxrail/__init__.py
staxrail/testrail.py
staxrail.egg-info/PKG-INFO
staxrail.egg-info/SOURCES.txt
staxrail.egg-info/dependency_links.txt
staxrail.egg-info/requires.txt
staxrail.egg-info/top_level.txt