Metadata-Version: 1.0
Name: staxrail
Version: 0.0.2
Summary: TestRail interface for Python 3 exposing more of the API
Home-page: https://github.com/gregfitch/staxrail
Author: OpenStax QA
Author-email: greg@openstax.org
License: Creative Commons Attribution 4.0 International Public License
Platform: UNKNOWN
